apple_notes_to_sqlite/__init__.py
apple_notes_to_sqlite/__main__.py
apple_notes_to_sqlite/cli.py
apple_notes_to_sqlite-0.1.dist-info/LICENSE
apple_notes_to_sqlite-0.1.dist-info/METADATA
apple_notes_to_sqlite-0.1.dist-info/WHEEL
apple_notes_to_sqlite-0.1.dist-info/entry_points.txt
apple_notes_to_sqlite-0.1.dist-info/top_level.txt
apple_notes_to_sqlite-0.1.dist-info/RECORD
