Metadata-Version: 2.1
Name: apple-notes-to-sqlite
Version: 0.1
Summary: Export Apple Notes to SQLite
Home-page: https://github.com/dogsheep/apple-notes-to-sqlite
Author: Simon Willison
License: Apache License, Version 2.0
Project-URL: Issues, https://github.com/dogsheep/apple-notes-to-sqlite/issues
Project-URL: CI, https://github.com/dogsheep/apple-notes-to-sqlite/actions
Project-URL: Changelog, https://github.com/dogsheep/apple-notes-to-sqlite/releases
Requires-Python: >=3.7
License-File: LICENSE
Requires-Dist: click
Requires-Dist: sqlite-utils
Provides-Extra: test
Requires-Dist: pytest ; extra == 'test'
Requires-Dist: pytest-subprocess ; extra == 'test'
